rtreecpy/__init__.py
rtreecpy/librtreec.so
rtreecpy/rtreec.py
rtreecpy-1.0.5.dist-info/LICENSE
rtreecpy-1.0.5.dist-info/METADATA
rtreecpy-1.0.5.dist-info/WHEEL
rtreecpy-1.0.5.dist-info/top_level.txt
rtreecpy-1.0.5.dist-info/RECORD
