Metadata-Version: 2.1
Name: rtreecpy
Version: 1.0.5
Summary: rtree c python bindings
Home-page: https://github.com/drorspei/rtree.c
Author: dror
Author-email: dror.mastershin@gmail.com
License: UNKNOWN
Platform: UNKNOWN
Classifier: Programming Language :: Python :: 3
Classifier: License :: OSI Approved :: MIT License
Classifier: Operating System :: OS Independent
License-File: LICENSE
